odoo10_addon_bi_sql_editor-10.0.1.0.2-py3.6-nspkg.pth
odoo/addons/bi_sql_editor/README.rst
odoo/addons/bi_sql_editor/__init__.py
odoo/addons/bi_sql_editor/__manifest__.py
odoo/addons/bi_sql_editor/hooks.py
odoo/addons/bi_sql_editor/demo/bi_sql_view_demo.xml
odoo/addons/bi_sql_editor/demo/res_groups_demo.xml
odoo/addons/bi_sql_editor/i18n/am.po
odoo/addons/bi_sql_editor/i18n/ar.po
odoo/addons/bi_sql_editor/i18n/bg.po
odoo/addons/bi_sql_editor/i18n/bi_sql_editor.pot
odoo/addons/bi_sql_editor/i18n/bs.po
odoo/addons/bi_sql_editor/i18n/ca.po
odoo/addons/bi_sql_editor/i18n/cs.po
odoo/addons/bi_sql_editor/i18n/da.po
odoo/addons/bi_sql_editor/i18n/de.po
odoo/addons/bi_sql_editor/i18n/el_GR.po
odoo/addons/bi_sql_editor/i18n/en_GB.po
odoo/addons/bi_sql_editor/i18n/es.po
odoo/addons/bi_sql_editor/i18n/es_AR.po
odoo/addons/bi_sql_editor/i18n/es_CL.po
odoo/addons/bi_sql_editor/i18n/es_CO.po
odoo/addons/bi_sql_editor/i18n/es_CR.po
odoo/addons/bi_sql_editor/i18n/es_DO.po
odoo/addons/bi_sql_editor/i18n/es_EC.po
odoo/addons/bi_sql_editor/i18n/es_ES.po
odoo/addons/bi_sql_editor/i18n/es_MX.po
odoo/addons/bi_sql_editor/i18n/es_PE.po
odoo/addons/bi_sql_editor/i18n/es_PY.po
odoo/addons/bi_sql_editor/i18n/es_VE.po
odoo/addons/bi_sql_editor/i18n/et.po
odoo/addons/bi_sql_editor/i18n/eu.po
odoo/addons/bi_sql_editor/i18n/fa.po
odoo/addons/bi_sql_editor/i18n/fi.po
odoo/addons/bi_sql_editor/i18n/fr.po
odoo/addons/bi_sql_editor/i18n/fr_CA.po
odoo/addons/bi_sql_editor/i18n/fr_CH.po
odoo/addons/bi_sql_editor/i18n/gl.po
odoo/addons/bi_sql_editor/i18n/gl_ES.po
odoo/addons/bi_sql_editor/i18n/he.po
odoo/addons/bi_sql_editor/i18n/hr.po
odoo/addons/bi_sql_editor/i18n/hr_HR.po
odoo/addons/bi_sql_editor/i18n/hu.po
odoo/addons/bi_sql_editor/i18n/id.po
odoo/addons/bi_sql_editor/i18n/it.po
odoo/addons/bi_sql_editor/i18n/ja.po
odoo/addons/bi_sql_editor/i18n/ko.po
odoo/addons/bi_sql_editor/i18n/lt.po
odoo/addons/bi_sql_editor/i18n/lt_LT.po
odoo/addons/bi_sql_editor/i18n/lv.po
odoo10_addon_bi_sql_editor-10.0.1.0.2.dist-info/METADATA
odoo10_addon_bi_sql_editor-10.0.1.0.2.dist-info/WHEEL
odoo10_addon_bi_sql_editor-10.0.1.0.2.dist-info/namespace_packages.txt
odoo10_addon_bi_sql_editor-10.0.1.0.2.dist-info/top_level.txt
odoo10_addon_bi_sql_editor-10.0.1.0.2.dist-info/RECORD
