Metadata-Version: 2.1
Name: odoo10-addon-bi-sql-editor
Version: 10.0.1.0.2
Summary: BI Views builder, based on Materialized or Normal SQL Views
Home-page: https://github.com/OCA/reporting-engine
Author: GRAP,Odoo Community Association (OCA)
Author-email: support@odoo-community.org
License: AGPL-3
Platform: UNKNOWN
Classifier: Programming Language :: Python
Classifier: Framework :: Odoo
Classifier: License :: OSI Approved :: GNU Affero General Public License v3
Requires-Python: ~=2.7
Requires-Dist: odoo10-addon-sql-request-abstract
Requires-Dist: odoo (<10.1dev,>=10.0)
